source_analyser/__init__.py
source_analyser/functions_to_print.py
source_analyser/opportunity.py
source_analyser/pipeline.py
source_analyser/utils.py
source_analyser/views.py
source_analyser-26.1.2022.2.dist-info/METADATA
source_analyser-26.1.2022.2.dist-info/WHEEL
source_analyser-26.1.2022.2.dist-info/top_level.txt
source_analyser-26.1.2022.2.dist-info/RECORD
