Metadata-Version: 2.1
Name: source-analyser
Version: 26.1.2022.2
Summary: Use to Analyse some oppies... for a specific use only!
Home-page: UNKNOWN
Author: Abdul Salam
Author-email: abdulsalamone@gmail.com
License: UNKNOWN
Keywords: python,expedia,source analyser
Platform: UNKNOWN
Classifier: Development Status :: 3 - Alpha
Classifier: Intended Audience :: Developers
Classifier: License :: OSI Approved :: MIT License
Classifier: Programming Language :: Python :: 3.6
Classifier: Programming Language :: Python :: 3.7
Classifier: Programming Language :: Python :: 3.8
Classifier: Programming Language :: Python :: 3.9
Classifier: Operating System :: OS Independent
Requires-Dist: json-minify (==0.3.0)
Requires-Dist: boto3 (==1.15.0)
Requires-Dist: sql-metadata (==2.3.0)
